redsys/__init__.py
redsys/client.py
redsys/constants.py
redsys/request.py
redsys/response.py
redsys/tests/__init__.py
redsys/tests/test_client.py
redsys/tests/test_request.py
redsys/tests/test_response.py
python_redsys-1.2.0.dist-info/LICENSE
python_redsys-1.2.0.dist-info/METADATA
python_redsys-1.2.0.dist-info/WHEEL
python_redsys-1.2.0.dist-info/RECORD
