Metadata-Version: 2.1
Name: python-redsys
Version: 1.2.0
Summary: A simple, clean and less dependant client to handle payments through Redsys.
Home-page: https://github.com/systemallica/python-redsys
License: MIT
Author: Andrés Reverón Molina
Author-email: andres@reveronmolina.me
Requires-Python: >=3.8,<4.0
Classifier: Intended Audience :: Developers
Classifier: License :: OSI Approved :: MIT License
Classifier: Operating System :: OS Independent
Classifier: Programming Language :: Python :: 3
Classifier: Programming Language :: Python :: 3.8
Classifier: Programming Language :: Python :: 3.9
Classifier: Programming Language :: Python :: 3.10
Classifier: Programming Language :: Python :: 3.11
Requires-Dist: pycryptodome (>=3.19.0,<4.0.0)
